{
  "textureCount": 1,
  "textures": [
    {
      "textureName": "background",
      "textureLoc": "MenuBg.png"
    }
  ],
  "objectCount": 4,
  "objects": [
    {
      "name": "background",
      "size": [ 1920, 1080 ],
      "textureName": "background"
    },
    {
      "name": "playButton",
      "size": [ 400, 200 ],
      "position": [ 760, 430 ],
      "textureName": "empty"
    },
    {
      "name": "settingsButton",
      "size": [ 400, 200 ],
      "position": [ 760, 640 ],
      "textureName": "empty"
    },
    {
      "name": "exitButton",
      "size": [ 400, 200 ],
      "position": [ 760, 850 ],
      "textureName": "empty"
    }
  ]
}
